{"frames":{"parkimeter":{"frame":{"x":4,"y":4,"w":347,"h":76},"rotated":false,"trimmed":false,"spriteSourceSize":{"x":0,"y":0,"w":347,"h":76},"sourceSize":{"w":347,"h":76}},"tires":{"frame":{"x":360,"y":4,"w":141,"h":93},"rotated":false,"trimmed":false,"spriteSourceSize":{"x":0,"y":0,"w":141,"h":93},"sourceSize":{"w":141,"h":93}},"dumpster":{"frame":{"x":4,"y":88,"w":79,"h":121},"rotated":false,"trimmed":false,"spriteSourceSize":{"x":0,"y":0,"w":79,"h":121},"sourceSize":{"w":79,"h":121}},"payphone":{"frame":{"x":92,"y":88,"w":60,"h":141},"rotated":false,"trimmed":false,"spriteSourceSize":{"x":0,"y":0,"w":60,"h":141},"sourceSize":{"w":60,"h":141}},"mailbox":{"frame":{"x":160,"y":88,"w":79,"h":98},"rotated":false,"trimmed":false,"spriteSourceSize":{"x":0,"y":0,"w":79,"h":98},"sourceSize":{"w":79,"h":98}},"news":{"frame":{"x":248,"y":88,"w":97,"h":53},"rotated":false,"trimmed":false,"spriteSourceSize":{"x":0,"y":0,"w":97,"h":53},"sourceSize":{"w":97,"h":53}},"gcan":{"frame":{"x":160,"y":196,"w":71,"h":51},"rotated":false,"trimmed":false,"spriteSourceSize":{"x":0,"y":0,"w":71,"h":51},"sourceSize":{"w":71,"h":51}}},"meta":{"app":"http://www.leshylabs.com/apps/sstool/","version":"Leshy SpriteSheet Tool v0.8.1","size":{"w":512,"h":256},"scale":1}}